<?xml version="1.0" encoding="utf-8" ?>
<ZetboxConfig xmlns="http://dasz.at/Zetbox/">
  <ConfigName>zetbox.Workflow Server Cli Configuration</ConfigName>
  <Server StartServer="true">
    <ConnectionStrings>
      <Database Name="Zetbox" Schema="MSSQL" Provider="System.Data.SqlClient">Data Source=.\SQLEXPRESS;Initial Catalog=Workflow;Integrated Security=True;MultipleActiveResultSets=true;</Database>
    </ConnectionStrings>
    <DocumentStore>DocumentStore\Server\</DocumentStore>
    <CodeGenWorkingPath>..\CodeGenNext</CodeGenWorkingPath>
    <CodeGenOutputPath>..\CodeGen</CodeGenOutputPath>
    <CodeGenArchivePath>..\Backup</CodeGenArchivePath>
    <Modules>
      <Module>Zetbox.Server.UnifiedModule, Zetbox.Server</Module>

      <Module>Zetbox.Objects.EfModule, Zetbox.Objects.EfImpl</Module>
      <Module>Zetbox.DalProvider.Ef.EfProvider, Zetbox.DalProvider.Ef</Module>

      <Module>Zetbox.App.Projekte.Server.CustomServerActionsModule, Zetbox.App.Projekte.Server</Module>
      <Module>Zetbox.App.Projekte.Common.CustomCommonActionsModule, Zetbox.App.Projekte.Common</Module>
      <!--
      <Module>Zetbox.Unix.Module, Zetbox.Unix</Module>
      <Module>Zetbox.Server.HtpasswdIdentitySource+Module, Zetbox.Server</Module>
      -->

      <!-- Development/Master Server modules -->
      <Module>Zetbox.Generator.GeneratorModule, Zetbox.Generator</Module>
      <Module>Zetbox.DalProvider.Memory.Generator.MemoryGeneratorProvider, Zetbox.DalProvider.Memory.Generator</Module>
      <Module>Zetbox.DalProvider.Ef.Generator.EfGeneratorProvider, Zetbox.DalProvider.Ef.Generator</Module>
      <Module>Zetbox.DalProvider.Client.Generator.ClientGeneratorProvider, Zetbox.DalProvider.Client.Generator</Module>
    </Modules>
  </Server>
  <AssemblySearchPaths>
    <string>Common\Core</string>
    <string>Common\Core.Fallback</string>
    <string>Server\Core</string>
    <string>Server\EF</string>
    <string>Server\EF.Fallback</string>
    <string>Common\App.Zetbox</string>
    <string>Server\App.Zetbox</string>
  </AssemblySearchPaths>
</ZetboxConfig>